modularity_encoding/__init__.py
modularity_encoding/functions.py
modularity_encoding/setup.py
modularity_encoding-0.2.dist-info/LICENSE.txt
modularity_encoding-0.2.dist-info/METADATA
modularity_encoding-0.2.dist-info/WHEEL
modularity_encoding-0.2.dist-info/top_level.txt
modularity_encoding-0.2.dist-info/RECORD
