Metadata-Version: 2.1
Name: modularity_encoding
Version: 0.2
Summary: A package to group healthcode systems using network analysis modularity
Home-page: https://github.com/MohsenAskar
Author: Mohsen Askar
Author-email: ceaser198511@gmail.com
License: MIT
Classifier: Programming Language :: Python :: 3
Classifier: License :: OSI Approved :: MIT License
License-File: LICENSE.txt
Requires-Dist: numpy
Requires-Dist: pandas
Requires-Dist: networkx
Requires-Dist: python-louvain
Requires-Dist: tqdm
Requires-Dist: matplotlib
